README.rst
setup.py
vexatapi/__init__.py
vexatapi/vexata_api_proxy.py
vexatapi.egg-info/PKG-INFO
vexatapi.egg-info/SOURCES.txt
vexatapi.egg-info/dependency_links.txt
vexatapi.egg-info/requires.txt
vexatapi.egg-info/top_level.txt