Metadata-Version: 1.0
Name: vexatapi
Version: 0.0.2
Summary: Python API for Vexata Storage Arrays
Home-page: https://github.com/vexata/vexatapi
Author: Sandeep Kasargod
Author-email: python-dev@vexata.com
License: Apache 2.0
Platform: UNKNOWN
